elevenlabs_bulk/__init__.py
elevenlabs_bulk/cant_use_elb.py
elevenlabs_bulk/fix_bug_.py
elevenlabs_bulk/fix_bug_elb.py
elevenlabs_bulk/sandbox1_.py
elevenlabs_bulk-0.1.0.dist-info/METADATA
elevenlabs_bulk-0.1.0.dist-info/WHEEL
elevenlabs_bulk-0.1.0.dist-info/top_level.txt
elevenlabs_bulk-0.1.0.dist-info/RECORD
