Metadata-Version: 2.1
Name: elevenlabs-bulk
Version: 0.1.0
Summary: create multiple audio files at once
Home-page: UNKNOWN
Author: Dear Norathee
License: MIT
Platform: UNKNOWN
Requires-Dist: pandas
Requires-Dist: os-toolkit (>=0.1.1)
Requires-Dist: py-string-tool (>=0.1.3)
Requires-Dist: python-wizard (>=0.1.1)
